ldif2csv.py
ldif2csv-1.0.1.dist-info/METADATA
ldif2csv-1.0.1.dist-info/WHEEL
ldif2csv-1.0.1.dist-info/entry_points.txt
ldif2csv-1.0.1.dist-info/top_level.txt
ldif2csv-1.0.1.dist-info/RECORD
