Metadata-Version: 2.1
Name: ldif2csv
Version: 1.0.1
Summary: Conversion tool for LDIF to CSV
License: MIT
Project-URL: repository, https://github.com/pfptcommunity/ldif2csv
Requires-Python: >3.9
Requires-Dist: ldif
